rox_control/__init__.py
rox_control/py.typed
rox_control/track.py
rox_control/version.py
rox_control/controllers/__init__.py
rox_control/controllers/pure_pursuit_a.py
rox_control/tools/__init__.py
rox_control/tools/bicicle_model.py
rox_control/tools/plot.py
rox_control/tools/simulation.py
rox_control/tools/tracks.py
rox_control-0.4.0.dist-info/licenses/LICENCE
rox_control-0.4.0.dist-info/METADATA
rox_control-0.4.0.dist-info/WHEEL
rox_control-0.4.0.dist-info/top_level.txt
rox_control-0.4.0.dist-info/RECORD
