Metadata-Version: 2.4
Name: rox-control
Version: 0.4.0
Summary: Controllers for path following
Author-email: ROX Automation <jev.kuznetsov@gmail.com>
License-Expression: MIT
Project-URL: Homepage, https://github.com/rox-automation/rox-control
Classifier: Development Status :: 3 - Alpha
Classifier: Intended Audience :: Developers
Classifier: Operating System :: OS Independent
Classifier: Programming Language :: Python
Classifier: Programming Language :: Python :: 3.11
Classifier: Topic :: Software Development :: Libraries :: Python Modules
Classifier: Typing :: Typed
Requires-Python: >=3.11
License-File: LICENCE
Requires-Dist: rox-vectors
Requires-Dist: numpy
Provides-Extra: tools
Requires-Dist: matplotlib; extra == "tools"
Provides-Extra: dev
Requires-Dist: pytest; extra == "dev"
Requires-Dist: pytest-cov; extra == "dev"
Requires-Dist: mypy; extra == "dev"
Requires-Dist: ruff; extra == "dev"
Requires-Dist: invoke; extra == "dev"
Requires-Dist: pre-commit; extra == "dev"
Requires-Dist: matplotlib; extra == "dev"
Dynamic: license-file
